twitter_botblocker/__init__.py
twitter_botblocker/main.py
twitter_botblocker-0.1.0.dist-info/METADATA
twitter_botblocker-0.1.0.dist-info/WHEEL
twitter_botblocker-0.1.0.dist-info/entry_points.txt
twitter_botblocker-0.1.0.dist-info/RECORD
