Metadata-Version: 2.1
Name: twitter_botblocker
Version: 0.1.0
Summary: 
Author: sweatrs
Requires-Python: >=3.11,<4.0
Classifier: Programming Language :: Python :: 3
Classifier: Programming Language :: Python :: 3.11
Classifier: Programming Language :: Python :: 3.12
Requires-Dist: asyncclick (>=8.1.7.2,<9.0.0.0)
Requires-Dist: rich (>=13.7.1,<14.0.0)
Requires-Dist: twikit (>=2.0.2,<3.0.0)
